appnigma_integrations_client/__init__.py
appnigma_integrations_client/client.py
appnigma_integrations_client/errors.py
appnigma_integrations_client/types.py
appnigma_integrations_client-0.1.3.dist-info/METADATA
appnigma_integrations_client-0.1.3.dist-info/WHEEL
appnigma_integrations_client-0.1.3.dist-info/top_level.txt
appnigma_integrations_client-0.1.3.dist-info/RECORD
