Metadata-Version: 2.4
Name: appnigma-integrations-client
Version: 0.1.3
Summary: Official Python SDK for Appnigma Integrations API
Author-email: Appnigma <support@appnigma.ai>
License: MIT
Project-URL: Homepage, https://github.com/appnigma/appnigma-integrations-python
Project-URL: Repository, https://github.com/appnigma/appnigma-integrations-python
Project-URL: Issues, https://github.com/appnigma/appnigma-integrations-python/issues
Keywords: appnigma,salesforce,integration,sdk
Classifier: Development Status :: 4 - Beta
Classifier: Intended Audience :: Developers
Classifier: License :: OSI Approved :: MIT License
Classifier: Programming Language :: Python :: 3
Classifier: Programming Language :: Python :: 3.8
Classifier: Programming Language :: Python :: 3.9
Classifier: Programming Language :: Python :: 3.10
Classifier: Programming Language :: Python :: 3.11
Classifier: Programming Language :: Python :: 3.12
Requires-Python: >=3.8
Requires-Dist: aiohttp>=3.8.0
Requires-Dist: typing_extensions>=4.0.0; python_version < "3.11"
